streamlit_pandas/__init__.py
streamlit_pandas/streamlit_pandas.py
streamlit_pandas-0.0.8.dist-info/METADATA
streamlit_pandas-0.0.8.dist-info/WHEEL
streamlit_pandas-0.0.8.dist-info/top_level.txt
streamlit_pandas-0.0.8.dist-info/RECORD
